roobet/__init__.py
roobet/roobet.py
roobet-0.0.1.dist-info/LICENSE
roobet-0.0.1.dist-info/METADATA
roobet-0.0.1.dist-info/WHEEL
roobet-0.0.1.dist-info/top_level.txt
roobet-0.0.1.dist-info/RECORD
