Metadata-Version: 2.1
Name: roobet
Version: 0.0.1
Summary: Python library for querying Roobet Crash games
Home-page: https://github.com/drewnicolette/roobet
Author: Drew Nicolette
Author-email: nicolettedrew0@gmail.com
License: MIT
Platform: UNKNOWN
Classifier: Programming Language :: Python :: 3
Classifier: License :: OSI Approved :: MIT License
Classifier: Operating System :: OS Independent
License-File: LICENSE
Requires-Dist: hashlib
Requires-Dist: hmac
